tcia_utils/__init__.py
tcia_utils/datacite.py
tcia_utils/nbia.py
tcia_utils/nbia_v4.py
tcia_utils/pathdb.py
tcia_utils/utils.py
tcia_utils/wordpress.py
tcia_utils-3.2.1.dist-info/METADATA
tcia_utils-3.2.1.dist-info/WHEEL
tcia_utils-3.2.1.dist-info/licenses/LICENSE
tcia_utils-3.2.1.dist-info/RECORD
