Metadata-Version: 2.4
Name: tcia_utils
Version: 3.2.1
Summary: A package to simplify common tasks one might perform when interacting with The Cancer Imaging Archive (TCIA) via Jupyter/Python.
Project-URL: Homepage, https://github.com/kirbyju/tcia_utils
Project-URL: Bug Tracker, https://github.com/kirbyju/tcia_utils/issues
Author-email: Justin Kirby <justin.kirby@nih.gov>
License-File: LICENSE
Classifier: License :: OSI Approved :: Apache Software License
Classifier: Operating System :: OS Independent
Classifier: Programming Language :: Python :: 3
Requires-Python: >=3.9
Requires-Dist: bs4
Requires-Dist: ipython
Requires-Dist: pandas
Requires-Dist: plotly
Requires-Dist: requests
Requires-Dist: tqdm
Requires-Dist: unidecode
Provides-Extra: test
Requires-Dist: pytest; extra == 'test'
Requires-Dist: pytest-mock; extra == 'test'
